weavearc/__init__.py
weavearc/contracts.py
weavearc/extensions.py
weavearc/logging.py
weavearc/py.typed
weavearc/data/__init__.py
weavearc/data/files.py
weavearc/data/repositories.py
weavearc/data/schema.py
weavearc/utils/__init__.py
weavearc/utils/builders.py
weavearc/utils/creators.py
weavearc/utils/decorators.py
weavearc/utils/functions.py
weavearc/utils/markers.py
weavearc-0.3.1.dist-info/METADATA
weavearc-0.3.1.dist-info/WHEEL
weavearc-0.3.1.dist-info/RECORD
