Metadata-Version: 2.3
Name: weavearc
Version: 0.3.1
Summary: weavearc is a lightweight, comprehensive framework that empowers developers to create robust, maintainable applications. By adhering to clean architecture principles and domain-driven design (DDD) patterns, weavearc provides the foundational building blocks needed for scalable, flexible, and easily testable backends. Simplify the complex and build with confidence across any architecture.
Requires-Python: >=3.10
Requires-Dist: aiocache>=0.12.3
Requires-Dist: msgspec>=0.18.6
Requires-Dist: pydantic>=2.9.2
Requires-Dist: rich>=13.9.4
